jajucha/ABOUT.txt
jajucha/CREDITS.txt
jajucha/__init__.py
jajucha/communication.py
jajucha/config.py
jajucha/control.py
jajucha/graphics.py
jajucha/planning.py
jajucha-2.2.3.dist-info/LICENSE-3RD-PARTY.txt
jajucha-2.2.3.dist-info/LICENSE.txt
jajucha-2.2.3.dist-info/METADATA
jajucha-2.2.3.dist-info/WHEEL
jajucha-2.2.3.dist-info/top_level.txt
jajucha-2.2.3.dist-info/RECORD
