Metadata-Version: 2.1
Name: jajucha
Version: 2.2.3
Summary: Controller Library for jajucha, a model car for autonomous driving education.
Home-page: https://github.com/gyusang/jajucha
Author: Sanggyu Lee
Author-email: sanggyu523@naver.com
License: MIT
Download-URL: https://github.com/gyusang/jajucha/archive/v_2_2_3.tar.gz
Project-URL: Source, https://github.com/gyusang/jajucha
Project-URL: Report Bugs, https://github.com/gyusang/jajucha/issues
Keywords: education,autonomous driving,jajucha,자주차
Platform: UNKNOWN
Classifier: Development Status :: 3 - Alpha
Classifier: Intended Audience :: Education
Classifier: Operating System :: Microsoft :: Windows
Classifier: Operating System :: Microsoft :: Windows :: Windows 10
Classifier: Topic :: Education
Classifier: Topic :: Scientific/Engineering :: Artificial Intelligence
Classifier: Topic :: Scientific/Engineering :: Image Processing
Classifier: License :: OSI Approved :: MIT License
Classifier: Programming Language :: Python :: 3
Requires-Python: ~=3.7
License-File: LICENSE.txt
License-File: LICENSE-3RD-PARTY.txt
Requires-Dist: numpy (!=1.19.4)
Requires-Dist: opencv-python
Requires-Dist: pyzmq
Requires-Dist: imagezmq
Requires-Dist: pillow
Requires-Dist: scipy
